salusshcpy/__init__.py
salusshcpy/api.py
salusshcpy/const.py
salusshcpy/device.py
salusshcpy/device_helper.py
salusshcpy/encryptor.py
salusshcpy/information.py
salusshcpy/models_impl.py
salusshcpy/session.py
salusshcpy-0.0.19.dist-info/METADATA
salusshcpy-0.0.19.dist-info/WHEEL
salusshcpy-0.0.19.dist-info/top_level.txt
salusshcpy-0.0.19.dist-info/RECORD
